ngspicejson/__init__.py
ngspicejson/config.py
ngspicejson/ngspice_json_cli.py
ngspicejson/app/__init__.py
ngspicejson/app/run.py
ngspicejson/app/api/__init__.py
ngspicejson/app/api/run.py
ngspicejson/app/api/version.py
ngspicejson/service/__init__.py
ngspicejson/service/business/__init__.py
ngspicejson/service/business/debug_message.py
ngspicejson/service/business/ngspice_error_message.py
ngspicejson/service/business/preordered_ngspice_command.py
ngspicejson/service/business/simulate_ngspice.py
ngspicejson/service/parse/__init__.py
ngspicejson/service/parse/abstract_parse.py
ngspicejson/service/parse/parse_initial_transient_solution.py
ngspicejson/service/parse/parse_model_list.py
ngspicejson/service/parse/parse_ngspice_version.py
ngspicejson/service/parse/parse_print_tabular_contents.py
ngspicejson/service/parse/parse_specific_print.py
ngspicejson/service/tool/__init__.py
ngspicejson/service/tool/decorator.py
ngspicejson/service/tool/exception.py
ngspicejson/service/tool/marshal.py
ngspicejson/service/tool/ngspice_tool.py
ngspicejson/test/__init__.py
ngspicejson/test/command/__init__.py
ngspicejson/test/command/initial_transient_solution.py
ngspicejson/test/command/ngspice_version.py
ngspicejson/test/command/print_tabular_contents.py
ngspicejson/test/command/show_all.py
ngspicejson/test/command/specific_print.py
ngspice_json_cli-0.0.13.dist-info/METADATA
ngspice_json_cli-0.0.13.dist-info/WHEEL
ngspice_json_cli-0.0.13.dist-info/top_level.txt
ngspice_json_cli-0.0.13.dist-info/RECORD
